file_size/__init__.py
file_size/size.py
file_size-0.0.1.dist-info/METADATA
file_size-0.0.1.dist-info/WHEEL
file_size-0.0.1.dist-info/entry_points.txt
file_size-0.0.1.dist-info/top_level.txt
file_size-0.0.1.dist-info/RECORD
