Metadata-Version: 2.1
Name: file-size
Version: 0.0.1
Summary: It's a simple python package to calculate the file size.
Author: Kauã Fabricio
Author-email: kauafabriiciio@gmail.com
Requires-Python: >=3.0
